prediction_coefficient/__init__.py
prediction_coefficient/categorical_prediction_coefficient.py
prediction_coefficient-0.0.0.dist-info/LICENSE
prediction_coefficient-0.0.0.dist-info/METADATA
prediction_coefficient-0.0.0.dist-info/WHEEL
prediction_coefficient-0.0.0.dist-info/top_level.txt
prediction_coefficient-0.0.0.dist-info/RECORD
